{
    "tex": {
        "main": {
            ":desc:": "#### Main rules for standard ``(La)TeX`` projects, see https://github.com/latex3.",
            ":rules-n-comments:": [
                {
                    ":comments:": "## Core latex/pdflatex",
                    ":rules:": [
                        "*.aux",
                        "*.cb",
                        "*.cb2",
                        "*.fls",
                        "*.f[om]t",
                        "*.lo[fgt]",
                        ".*.lb",
                        "*.out",
                        "*.toc"
                    ]
                },
                {
                    ":comments:": "## Intermediate documents",
                    ":rules:": [
                        "*.dvi",
                        "*.xdv",
                        "*-converted-to.*"
                    ]
                },
                {
                    ":comments:": "## Generated if empty string is given at\n## \"Please type another file name for output:\".",
                    ":rules:": [
                        ".pdf"
                    ]
                },
                {
                    ":comments:": "## Extra \"standard\" tools.",
                    ":rules:": [
                        "*.fdb_latexmk",
                        "*.synctex",
                        "*.synctex(busy)",
                        "*.synctex.gz",
                        "*.synctex.gz(busy)",
                        "*.pdfsync"
                    ]
                }
            ]
        },
        "packages": {
            "music": {
                "gregoriotex": {
                    ":desc:": "#### Specific rules for the package ``gregoriotex``.",
                    ":rules-n-comments:": [
                        {
                            ":comments:": "##",
                            ":rules:": [
                                "*.gaux",
                                "*.glog",
                                "*.gtex"
                            ]
                        }
                    ]
                }
            },
            "bibliography": {
                "biblio": {
                    ":desc:": "#### Specific rules for bibliographies.",
                    ":rules-n-comments:": [
                        {
                            ":comments:": "##",
                            ":rules:": [
                                "*.bbl",
                                "*.bcf",
                                "*.blg",
                                "*-blx.aux",
                                "*-blx.bib",
                                "*.run.xml"
                            ]
                        }
                    ]
                }
            },
            "computer-science": {
                "algorithms": {
                    ":desc:": "#### Specific rules for the package ``algorithms``.",
                    ":rules-n-comments:": [
                        {
                            ":comments:": "##",
                            ":rules:": [
                                "*.alg",
                                "*.loa"
                            ]
                        }
                    ]
                }
            },
            "science": {
                "gnuplottex": {
                    ":desc:": "#### Specific rules for the package ``gnuplottex``.",
                    ":rules-n-comments:": [
                        {
                            ":comments:": "##",
                            ":rules:": [
                                "*-gnuplottex-*"
                            ]
                        }
                    ]
                },
                "sympytex": {
                    ":desc:": "#### Specific rules for the package ``sympytex``.",
                    ":rules-n-comments:": [
                        {
                            ":comments:": "##",
                            ":rules:": [
                                "*.sout",
                                "*.sympy",
                                "sympy-plots-for-*.tex/"
                            ]
                        }
                    ]
                },
                "sagetex": {
                    ":desc:": "#### Specific rules for the package ``sagetex``.",
                    ":rules-n-comments:": [
                        {
                            ":comments:": "##",
                            ":rules:": [
                                "*.sagetex.sage",
                                "*.sagetex.py",
                                "*.sagetex.scmd"
                            ]
                        }
                    ]
                },
                "feynmfp": {
                    ":desc:": "#### Specific rules for the packages ``feynmf`` and ``feynmp``.",
                    ":rules-n-comments:": [
                        {
                            ":comments:": "##",
                            ":rules:": [
                                "*.m[fp]",
                                "*.t[1-9]",
                                "*.t[1-9][0-9]",
                                "*.tfm"
                            ]
                        }
                    ]
                }
            },
            "pdf": {
                "pdfpc": {
                    ":desc:": "#### Specific rules for the package ``pdfpc``.",
                    ":rules-n-comments:": [
                        {
                            ":comments:": "##",
                            ":rules:": [
                                "*.pdfpc"
                            ]
                        }
                    ]
                },
                "newpax": {
                    ":desc:": "#### Specific rules for the package ``newpax``.",
                    ":rules-n-comments:": [
                        {
                            ":comments:": "##",
                            ":rules:": [
                                "*.newpax"
                            ]
                        }
                    ]
                },
                "xmpincl": {
                    ":desc:": "#### Specific rules for the package ``xmpincl``.",
                    ":rules-n-comments:": [
                        {
                            ":comments:": "##",
                            ":rules:": [
                                "*.xmpi"
                            ]
                        }
                    ]
                },
                "pdfcomment": {
                    ":desc:": "#### Specific rules for the package ``pdfcomment``.",
                    ":rules-n-comments:": [
                        {
                            ":comments:": "##",
                            ":rules:": [
                                "*.upa",
                                "*.upb"
                            ]
                        }
                    ]
                },
                "pax": {
                    ":desc:": "#### Specific rules for the package ``pax``.",
                    ":rules-n-comments:": [
                        {
                            ":comments:": "##",
                            ":rules:": [
                                "*.pax"
                            ]
                        }
                    ]
                }
            },
            "html": {
                "htlatex": {
                    ":desc:": "#### Specific rules for the tool ``htlatex``.",
                    ":rules-n-comments:": [
                        {
                            ":comments:": "##",
                            ":rules:": [
                                "*.4ct",
                                "*.4tc",
                                "*.idv",
                                "*.lg",
                                "*.trc",
                                "*.xref"
                            ]
                        }
                    ]
                }
            },
            "editing": {
                "achemso": {
                    ":desc:": "#### Specific rules for the package ``achemso``.",
                    ":rules-n-comments:": [
                        {
                            ":comments:": "##",
                            ":rules:": [
                                "acs-*.bib"
                            ]
                        }
                    ]
                },
                "elsarticle": {
                    ":desc:": "#### Specific rules for the package ``elsarticle`` (documentclass of Elsevier journals).",
                    ":rules-n-comments:": [
                        {
                            ":comments:": "##",
                            ":rules:": [
                                "*.spl"
                            ]
                        }
                    ]
                },
                "ledmac": {
                    ":desc:": "#### Specific rules for the package ``(r)(e)ledmac`` and ``(r)(e)ledpar``.",
                    ":rules-n-comments:": [
                        {
                            ":comments:": "##",
                            ":rules:": [
                                "*.end",
                                "*.?end",
                                "*.[1-9]",
                                "*.[1-9][0-9]",
                                "*.[1-9][0-9][0-9]",
                                "*.[1-9]R",
                                "*.[1-9][0-9]R",
                                "*.[1-9][0-9][0-9]R",
                                "*.eledsec[1-9]",
                                "*.eledsec[1-9]R",
                                "*.eledsec[1-9][0-9]",
                                "*.eledsec[1-9][0-9]R",
                                "*.eledsec[1-9][0-9][0-9]",
                                "*.eledsec[1-9][0-9][0-9]R"
                            ]
                        }
                    ]
                }
            },
            "formatting": {
                "tcolorbox": {
                    ":desc:": "#### Specific rules for the package ``tcolorbox``.",
                    ":rules-n-comments:": [
                        {
                            ":comments:": "##",
                            ":rules:": [
                                "*.listing"
                            ]
                        }
                    ]
                },
                "thmtools": {
                    ":desc:": "#### Specific rules for the package ``thmtools``.",
                    ":rules-n-comments:": [
                        {
                            ":comments:": "##",
                            ":rules:": [
                                "*.loe"
                            ]
                        }
                    ]
                },
                "xcolor": {
                    ":desc:": "#### Specific rules for the package ``xcolor``.",
                    ":rules-n-comments:": [
                        {
                            ":comments:": "##",
                            ":rules:": [
                                "*.xcp"
                            ]
                        }
                    ]
                },
                "beamer": {
                    ":desc:": "#### Specific rules for the package ``beamer``.",
                    ":rules-n-comments:": [
                        {
                            ":comments:": "##",
                            ":rules:": [
                                "*.nav",
                                "*.pre",
                                "*.snm",
                                "*.vrb"
                            ]
                        }
                    ]
                },
                "amsthm": {
                    ":desc:": "#### Specific rules for the package ``amsthm``.",
                    ":rules-n-comments:": [
                        {
                            ":comments:": "##",
                            ":rules:": [
                                "*.thm"
                            ]
                        }
                    ]
                },
                "xwatermark": {
                    ":desc:": "#### Specific rules for the package ``xwatermark``.",
                    ":rules-n-comments:": [
                        {
                            ":comments:": "##",
                            ":rules:": [
                                "*.xwm"
                            ]
                        }
                    ]
                },
                "standalone": {
                    ":desc:": "#### Specific rules for the package ``standalone``.",
                    ":rules-n-comments:": [
                        {
                            ":comments:": "##",
                            ":rules:": [
                                "*.sta"
                            ]
                        }
                    ]
                },
                "endfloat": {
                    ":desc:": "#### Specific rules for the package ``endfloat``.",
                    ":rules-n-comments:": [
                        {
                            ":comments:": "##",
                            ":rules:": [
                                "*.ttt",
                                "*.fff"
                            ]
                        }
                    ]
                },
                "endnotes": {
                    ":desc:": "#### Specific rules for the package ``endnotes``.",
                    ":rules-n-comments:": [
                        {
                            ":comments:": "##",
                            ":rules:": [
                                "*.ent"
                            ]
                        }
                    ]
                }
            },
            "linguistic": {
                "expex": {
                    ":desc:": "#### Specific rules for the package ``expex``.",
                    ":rules-n-comments:": [
                        {
                            ":comments:": "## Forward references with \\gathertags.",
                            ":rules:": [
                                "*-tags.tex"
                            ]
                        }
                    ]
                },
                "minted": {
                    ":desc:": "#### Specific rules for the package ``minted``.",
                    ":rules-n-comments:": [
                        {
                            ":comments:": "##",
                            ":rules:": [
                                "_minted*",
                                "*.pyg"
                            ]
                        }
                    ]
                }
            },
            "dev": {
                "vhistory": {
                    ":desc:": "#### Specific rules for the package ``vhistory``.",
                    ":rules-n-comments:": [
                        {
                            ":comments:": "##",
                            ":rules:": [
                                "*.hst",
                                "*.ver"
                            ]
                        }
                    ]
                },
                "fixme": {
                    ":desc:": "#### Specific rules for the package ``fixme``.",
                    ":rules-n-comments:": [
                        {
                            ":comments:": "##",
                            ":rules:": [
                                "*.lox"
                            ]
                        }
                    ]
                },
                "easy-todo": {
                    ":desc:": "#### Specific rules for the package ``easy-todo``.",
                    ":rules-n-comments:": [
                        {
                            ":comments:": "##",
                            ":rules:": [
                                "*.lod"
                            ]
                        }
                    ]
                },
                "morewrites": {
                    ":desc:": "#### Specific rules for the package ``morewrites``.",
                    ":rules-n-comments:": [
                        {
                            ":comments:": "##",
                            ":rules:": [
                                "*.mw"
                            ]
                        }
                    ]
                },
                "changes": {
                    ":desc:": "#### Specific rules for the package ``changes``.",
                    ":rules-n-comments:": [
                        {
                            ":comments:": "##",
                            ":rules:": [
                                "*.soc"
                            ]
                        }
                    ]
                },
                "cprotect": {
                    ":desc:": "#### Specific rules for the package ``cprotect``.",
                    ":rules-n-comments:": [
                        {
                            ":comments:": "##",
                            ":rules:": [
                                "*.cpt"
                            ]
                        }
                    ]
                },
                "todonotes": {
                    ":desc:": "#### Specific rules for the package ``todonotes``.",
                    ":rules-n-comments:": [
                        {
                            ":comments:": "##",
                            ":rules:": [
                                "*.tdo"
                            ]
                        }
                    ]
                },
                "comment": {
                    ":desc:": "#### Specific rules for the package ``comment``.",
                    ":rules-n-comments:": [
                        {
                            ":comments:": "##",
                            ":rules:": [
                                "*.cut"
                            ]
                        }
                    ]
                }
            },
            "listing": {
                "listings": {
                    ":desc:": "#### Specific rules for the package ``listings``.",
                    ":rules-n-comments:": [
                        {
                            ":comments:": "##",
                            ":rules:": [
                                "*.lol"
                            ]
                        }
                    ]
                }
            },
            "graphics": {
                "xypic": {
                    ":desc:": "#### Specific rules for the package ``xypic``.",
                    ":rules-n-comments:": [
                        {
                            ":comments:": "## Precompiled matrices and outlines",
                            ":rules:": [
                                "*.xy[cd]"
                            ]
                        }
                    ]
                },
                "tikz-pgf": {
                    ":desc:": "#### Specific rules for the packages ``TikZ`` and  ``PGF``.",
                    ":rules-n-comments:": [
                        {
                            ":comments:": "##",
                            ":rules:": [
                                "*.dpth",
                                "*.md5",
                                "*.auxlock"
                            ]
                        }
                    ]
                },
                "svg": {
                    ":desc:": "#### Specific rules for the package ``svg``.",
                    ":rules-n-comments:": [
                        {
                            ":comments:": "##",
                            ":rules:": [
                                "svg-inkscape/"
                            ]
                        }
                    ]
                }
            },
            "reference": {
                "titletoc": {
                    ":desc:": "#### Specific rules for the package ``titletoc``.",
                    ":rules-n-comments:": [
                        {
                            ":comments:": "##",
                            ":rules:": [
                                "*.ptc"
                            ]
                        }
                    ]
                },
                "makeidx": {
                    ":desc:": "#### Specific rules for the package ``makeidx``.",
                    ":rules-n-comments:": [
                        {
                            ":comments:": "##",
                            ":rules:": [
                                "*.idx",
                                "*.ilg",
                                "*.ind"
                            ]
                        }
                    ]
                },
                "minitoc": {
                    ":desc:": "#### Specific rules for the package ``minitoc``.",
                    ":rules-n-comments:": [
                        {
                            ":comments:": "##",
                            ":rules:": [
                                "*.maf",
                                "*.ml[ft]",
                                "*.mtc[0-9]*",
                                "*.sl[cft][0-9]*"
                            ]
                        }
                    ]
                },
                "xindy": {
                    ":desc:": "#### Specific rules for the package ``xindy``.",
                    ":rules-n-comments:": [
                        {
                            ":comments:": "##",
                            ":rules:": [
                                "*.xdy"
                            ]
                        }
                    ]
                },
                "glossaries": {
                    ":desc:": "#### Specific rules for the package ``glossaries``.",
                    ":rules-n-comments:": [
                        {
                            ":comments:": "##",
                            ":rules:": [
                                "*.ac[nr]",
                                "*.gl[gos]",
                                "*.glsdefs",
                                "*.lz[os]",
                                "*.sl[gos]"
                            ]
                        }
                    ]
                },
                "makeindex": {
                    ":desc:": "#### Specific rules for the standard tool ``Makeindex``.",
                    ":rules-n-comments:": [
                        {
                            ":comments:": "## Log files.",
                            ":rules:": [
                                "*.lpz"
                            ]
                        }
                    ]
                },
                "nomencl": {
                    ":desc:": "#### Specific rules for the package ``nomencl``.",
                    ":rules-n-comments:": [
                        {
                            ":comments:": "##",
                            ":rules:": [
                                "*.nl[gos]"
                            ]
                        }
                    ]
                },
                "hyperref": {
                    ":desc:": "#### Specific rules for the package ``hyperref``.",
                    ":rules-n-comments:": [
                        {
                            ":comments:": "##",
                            ":rules:": [
                                "*.brf"
                            ]
                        }
                    ]
                }
            },
            "extra-tools": {
                "pythontex": {
                    ":desc:": "#### Specific rules for the package ``pythontex``.",
                    ":rules-n-comments:": [
                        {
                            ":comments:": "##",
                            ":rules:": [
                                "*.pytxcode",
                                "pythontex-files-*/"
                            ]
                        }
                    ]
                },
                "scrwfile": {
                    ":desc:": "#### Specific rules for the package ``scrwfile``.",
                    ":rules-n-comments:": [
                        {
                            ":comments:": "##",
                            ":rules:": [
                                "*.wrt"
                            ]
                        }
                    ]
                }
            }
        },
        "editor": {
            "kbibtex": {
                ":desc:": "#### Specific rules for ``KBibTeX``, see https://apps.kde.org/fr/kbibtex/.",
                ":rules-n-comments:": [
                    {
                        ":comments:": "##",
                        ":rules:": [
                            "*~[0-9]*"
                        ]
                    }
                ]
            },
            "gummi": {
                ":desc:": "#### Specific rules for ``gummi``, see https://gummi.app/.",
                ":rules-n-comments:": [
                    {
                        ":comments:": "##",
                        ":rules:": [
                            ".*.swp"
                        ]
                    }
                ]
            },
            "kile": {
                ":desc:": "#### Specific rules for ``Kile``, see https://kile.sourceforge.io/.",
                ":rules-n-comments:": [
                    {
                        ":comments:": "##",
                        ":rules:": [
                            "*.backup"
                        ]
                    }
                ]
            },
            "lyx": {
                ":desc:": "#### Specific rules for ``LyX``, see https://www.lyx.org/.",
                ":rules-n-comments:": [
                    {
                        ":comments:": "##",
                        ":rules:": [
                            "*.lyx~"
                        ]
                    }
                ]
            },
            "emacs": {
                ":desc:": "#### Specific rules for ``emacs``, see https://www.gnu.org/software/emacs/.",
                ":rules-n-comments:": [
                    {
                        ":comments:": "## Auto folder when using auctex",
                        ":rules:": [
                            "./auto/*",
                            "*.el"
                        ]
                    }
                ]
            },
            "texniccenter": {
                ":desc:": "#### Specific rules for ``TeXnicCenter``, see https://www.texniccenter.org/.",
                ":rules-n-comments:": [
                    {
                        ":comments:": "##",
                        ":rules:": [
                            "*.tps"
                        ]
                    }
                ]
            },
            "texpad": {
                ":desc:": "#### Specific rules for ``Texpad``, see https://www.textpad.com/home.",
                ":rules-n-comments:": [
                    {
                        ":comments:": "##",
                        ":rules:": [
                            ".texpadtmp"
                        ]
                    }
                ]
            },
            "winedt": {
                ":desc:": "#### Specific rules for ``WinEdt``, see https://www.winedt.org/.",
                ":rules-n-comments:": [
                    {
                        ":comments:": "##",
                        ":rules:": [
                            "*.bak",
                            "*.sav"
                        ]
                    }
                ]
            }
        }
    },
    "python": {
        "main": {
            ":desc:": "#### Main rules for standard Python projects, see https://github.com/python/.",
            ":rules-n-comments:": [
                {
                    ":comments:": "## Byte-compiled",
                    ":rules:": [
                        "__pycache__/",
                        "*.py[co]"
                    ]
                },
                {
                    ":comments:": "## Cython debug",
                    ":rules:": [
                        "cython_debug/"
                    ]
                }
            ]
        },
        "tasks": {
            "celery": {
                ":desc:": "#### Specific rules for ``Celery``, see https://github.com/celery/celery/.",
                ":rules-n-comments:": [
                    {
                        ":comments:": "##",
                        ":rules:": [
                            "celerybeat-schedule",
                            "celerybeat.pid"
                        ]
                    }
                ]
            }
        },
        "web": {
            "flask": {
                ":desc:": "#### Specific rules for ``Flask``, see https://github.com/pallets/flask.",
                ":rules-n-comments:": [
                    {
                        ":comments:": "##",
                        ":rules:": [
                            "instance/",
                            ".webassets-cache"
                        ]
                    }
                ]
            },
            "django": {
                ":desc:": "#### Specific rules for ``Django``, see https://github.com/django/django.",
                ":rules-n-comments:": [
                    {
                        ":comments:": "##",
                        ":rules:": [
                            "*.log",
                            "local_settings.py",
                            "db.sqlite3",
                            "db.sqlite3-journal"
                        ]
                    }
                ]
            }
        },
        "science": {
            "jupyter": {
                ":desc:": "#### Specific rules for ``Jupyter``, see https://github.com/jupyter.",
                ":rules-n-comments:": [
                    {
                        ":comments:": "## Notebook",
                        ":rules:": [
                            ".ipynb_checkpoints"
                        ]
                    },
                    {
                        ":comments:": "## IPython",
                        ":rules:": [
                            "profile_default/",
                            "ipython_config.py"
                        ]
                    }
                ]
            },
            "sagemath": {
                ":desc:": "#### Specific rules for ``SageMath``, see https://www.sagemath.org.",
                ":rules-n-comments:": [
                    {
                        ":comments:": "##",
                        ":rules:": [
                            "*.sage.py"
                        ]
                    }
                ]
            }
        },
        "datas": {
            "scrapy": {
                ":desc:": "#### Specific rules for ``Scrapy``, see https://github.com/scrapy/scrapy.",
                ":rules-n-comments:": [
                    {
                        ":comments:": "##",
                        ":rules:": [
                            ".scrapy"
                        ]
                    }
                ]
            }
        },
        "dev": {
            "env": {
                ":desc:": "#### Specific rules for working with virtual environments.",
                ":rules-n-comments:": [
                    {
                        ":comments:": "##",
                        ":rules:": [
                            ".env",
                            ".venv",
                            "env/",
                            "venv/",
                            "ENV/",
                            "env.bak/",
                            "venv.bak/"
                        ]
                    },
                    {
                        ":comments:": "## pyenv",
                        ":rules:": [
                            ".python-version"
                        ]
                    },
                    {
                        ":comments:": "## pipenv",
                        ":rules:": [
                            "Pipfile.lock"
                        ]
                    }
                ]
            },
            "pybuilder": {
                ":desc:": "#### Specific rules for ``PyBuilder``, see https://github.com/pybuilder/pybuilder.",
                ":rules-n-comments:": [
                    {
                        ":comments:": "##",
                        ":rules:": [
                            ".pybuilder/",
                            "target/"
                        ]
                    }
                ]
            },
            "pyinstaller": {
                ":desc:": "#### Specific rules for ``PyInstaller``, see https://github.com/pyinstaller/pyinstaller.",
                ":rules-n-comments:": [
                    {
                        ":comments:": "##",
                        ":rules:": [
                            "*.manifest",
                            "*.spec"
                        ]
                    }
                ]
            },
            "testing": {
                ":desc:": "#### Specific rules for testing flow.",
                ":rules-n-comments:": [
                    {
                        ":comments:": "##",
                        ":rules:": [
                            ".tox/",
                            ".nox/",
                            "nosetests.xml",
                            ".pytest_cache/"
                        ]
                    },
                    {
                        ":comments:": "## Coverage",
                        ":rules:": [
                            "htmlcov/",
                            ".coverage",
                            ".coverage.*",
                            "coverage.xml",
                            "*.cover",
                            "*.py,cover",
                            "cover/"
                        ]
                    },
                    {
                        ":comments:": "##",
                        ":rules:": [
                            ".hypothesis/"
                        ]
                    }
                ]
            },
            "typing": {
                ":desc:": "#### Specific rules for typing specifications.",
                ":rules-n-comments:": [
                    {
                        ":comments:": "##",
                        ":rules:": [
                            ".mypy_cache/",
                            ".dmypy.json",
                            "dmypy.json"
                        ]
                    },
                    {
                        ":comments:": "##",
                        ":rules:": [
                            ".pyre/"
                        ]
                    },
                    {
                        ":comments:": "## pytype",
                        ":rules:": [
                            ".pytype/"
                        ]
                    }
                ]
            },
            "packaging": {
                ":desc:": "#### Specific rules for packaging projects.",
                ":rules-n-comments:": [
                    {
                        ":comments:": "##",
                        ":rules:": [
                            "MANIFEST.in"
                        ]
                    },
                    {
                        ":comments:": "##",
                        ":rules:": [
                            "build/",
                            "dist/",
                            "sdist/"
                        ]
                    },
                    {
                        ":comments:": "##",
                        ":rules:": [
                            "develop-eggs/",
                            "eggs/",
                            ".eggs/",
                            "*.egg-info/",
                            "*.egg"
                        ]
                    },
                    {
                        ":comments:": "##",
                        ":rules:": [
                            "wheels/",
                            "share/python-wheels/"
                        ]
                    },
                    {
                        ":comments:": "##",
                        ":rules:": [
                            "poetry.lock"
                        ]
                    },
                    {
                        ":comments:": "## pdm",
                        ":rules:": [
                            ".pdm.toml"
                        ]
                    }
                ]
            },
            "rope": {
                ":desc:": "#### Specific rules for ``Rope``, see https://github.com/python-rope/rope.",
                ":rules-n-comments:": [
                    {
                        ":comments:": "## Project settings",
                        ":rules:": [
                            ".ropeproject"
                        ]
                    }
                ]
            }
        },
        "os": {
            "windows": {
                ":desc:": "#### Specific rules for the ``Windows`` OS.",
                ":rules-n-comments:": [
                    {
                        ":comments:": "## DLL like",
                        ":rules:": [
                            "*.pyd"
                        ]
                    }
                ]
            }
        },
        "editor": {
            "spyder": {
                ":desc:": "#### Specific rules for ``Spyder``, see https://github.com/spyder-ide/spyder.",
                ":rules-n-comments:": [
                    {
                        ":comments:": "## Project settings",
                        ":rules:": [
                            ".spyderproject",
                            ".spyproject"
                        ]
                    }
                ]
            }
        }
    },
    "translate": {
        "gettext": {
            ":desc:": "#### Specific rules for ``gettext``, see https://www.gnu.org/software/gettext/.",
            ":rules-n-comments:": [
                {
                    ":comments:": "##",
                    ":rules:": [
                        "*.mo",
                        "*.pot"
                    ]
                }
            ]
        }
    },
    "doc": {
        "general": {
            "sphinx": {
                ":desc:": "#### Specific rules for ``Sphinx``, see https://github.com/sphinx-doc/sphinx.",
                ":rules-n-comments:": [
                    {
                        ":comments:": "##",
                        ":rules:": [
                            "docs/_build/"
                        ]
                    }
                ]
            }
        }
    }
}